counter/__init__.py
counter/admin.py
counter/apps.py
counter/models.py
counter/urls.py
counter/views.py
counter/migrations/0001_initial.py
counter/migrations/__init__.py
counter/tests/__init__.py
counter/tests/decorators.py
django_count_it-0.1.2.dist-info/LICENSE
django_count_it-0.1.2.dist-info/METADATA
django_count_it-0.1.2.dist-info/WHEEL
django_count_it-0.1.2.dist-info/top_level.txt
django_count_it-0.1.2.dist-info/RECORD
